[
    {
        "name":"jhon ibramim",
        "review":"5 star",
        "img":"./user1.jpg",
        "details":"its organization prhotgrapher is too skilled and well photographer",
        "id":1
    },
    {
        "name":"KaiSamer",
        "review":"4.5 star",
        "img":"./user2.jpg",
        "details":"its organization prhotgrapher is too skilled and well photographer",
        "id":2
    },
    {
        "name":"ms huja",
        "review":"4 star",
        "img":"./user5.jpg",
        "details":"its organization prhotgrapher is too skilled and well photographer",
        "id":3
    },
    {
        "name":"jiko",
        "review":"5 star",
        "img":"./user3.jpg",
        "details":"its organization prhotgrapher is too skilled and well photographer",
        "id":4
    },
    {
        "name":"leo markuis",
        "review":"4.5 star",
        "img":"./user4.jpg",
        "details":"its organization prhotgrapher is too skilled and well photographer",
        "id":5
    },
    {
        "name":"willium",
        "review":"4 star",
        "img":"./user5.jpg",
        "details":"its organization prhotgrapher is too skilled and well photographer",
        "id":6
    }
    
]